{
  "_meta": {
    "snapshot_id": "gic-health-portfolio",
    "description": "Full-fiscal-year health premium by insurer and carrier type, from the GI Council Segment-wise Report's Health Portfolio sheet. One row per fiscal_year × entity × carrier_group: tracked insurers (health retail / group / government / overseas-medical / grand total) plus aggregates — SAHI, GENERAL and INDUSTRY as printed; PSUs (sum of the 4 public-sector general insurers), Private (GENERAL − PSUs) and Others-retail (INDUSTRY retail − the named insurers) derived by exact arithmetic over rows printed in the same official table (each row's `basis` field says which). For each FY the newest GIC statement wins: a later report's restated prior-year comparative supersedes the year's own earlier edition. Missing is never zero.",
    "schema_version": "1.0.0",
    "dataset": "mixed",
    "last_updated": "2026-06-10",
    "last_successful_run": "2026-06-10T17:08:07.366Z",
    "upstream_sources": [
      "gi_council"
    ],
    "parser_status": "ready",
    "notes": "Filled by scripts/ingest/ingest-gicouncil-segment-annual.ts (npm run ingest:gic-segment-annual). gicouncil.in 403s datacenter IPs: live fetch needs an in-region run or INGEST_FETCH_PROXY; otherwise drop the official XLSX into data/raw/gicouncil/segment-annual/ — only March / 'final segment' editions count as full fiscal years."
  },
  "data": [
    {
      "fiscal_year": "FY23",
      "entity": "hdfc-ergo",
      "carrier_group": "general",
      "insurer_name": "HDFC Ergo General Insurance Co Ltd",
      "health_retail": 3440.48,
      "health_group": 1649.84,
      "health_govt": 0,
      "overseas_medical": 29.92,
      "health_total": 5120.24,
      "basis": "as printed in the report",
      "source_basis": "prior-year comparative columns",
      "period_label": "For the period up to March 2023",
      "provenance": {
        "source_name": "GI Council Segment-wise Report (upto March 2024 (FY24, provisional & unaudited)) — prior-year comparative columns",
        "source_url": "https://www.gicouncil.in/media/4418/segment_march_2024-16.xlsx",
        "source_file": "data/agent-pulls/gicouncil-segment/sources/segment_march_2024-16.xlsx",
        "source_period": "FY23",
        "fetched_at": "2026-06-10T17:04:18.008Z",
        "parsed_at": "2026-06-10T17:04:18.200Z",
        "parser_name": "ingest-gicouncil-segment-annual",
        "confidence": "high"
      }
    },
    {
      "fiscal_year": "FY23",
      "entity": "icici-lombard",
      "carrier_group": "general",
      "insurer_name": "ICICI Lombard General Insurance Co Ltd",
      "health_retail": 1037.22,
      "health_group": 3744.68,
      "health_govt": 0,
      "overseas_medical": 213.38,
      "health_total": 4995.28,
      "basis": "as printed in the report",
      "source_basis": "prior-year comparative columns",
      "period_label": "For the period up to March 2023",
      "provenance": {
        "source_name": "GI Council Segment-wise Report (upto March 2024 (FY24, provisional & unaudited)) — prior-year comparative columns",
        "source_url": "https://www.gicouncil.in/media/4418/segment_march_2024-16.xlsx",
        "source_file": "data/agent-pulls/gicouncil-segment/sources/segment_march_2024-16.xlsx",
        "source_period": "FY23",
        "fetched_at": "2026-06-10T17:04:18.008Z",
        "parsed_at": "2026-06-10T17:04:18.200Z",
        "parser_name": "ingest-gicouncil-segment-annual",
        "confidence": "high"
      }
    },
    {
      "fiscal_year": "FY23",
      "entity": "national-insurance",
      "carrier_group": "general",
      "insurer_name": "National Insurance Co Ltd",
      "health_retail": 2182.01,
      "health_group": 3879.88,
      "health_govt": 869.64,
      "overseas_medical": 3.32,
      "health_total": 6934.85,
      "basis": "as printed in the report",
      "source_basis": "prior-year comparative columns",
      "period_label": "For the period up to March 2023",
      "provenance": {
        "source_name": "GI Council Segment-wise Report (upto March 2024 (FY24, provisional & unaudited)) — prior-year comparative columns",
        "source_url": "https://www.gicouncil.in/media/4418/segment_march_2024-16.xlsx",
        "source_file": "data/agent-pulls/gicouncil-segment/sources/segment_march_2024-16.xlsx",
        "source_period": "FY23",
        "fetched_at": "2026-06-10T17:04:18.008Z",
        "parsed_at": "2026-06-10T17:04:18.200Z",
        "parser_name": "ingest-gicouncil-segment-annual",
        "confidence": "high"
      }
    },
    {
      "fiscal_year": "FY23",
      "entity": "new-india",
      "carrier_group": "general",
      "insurer_name": "The New India Assurance Co Ltd",
      "health_retail": 2697.07,
      "health_group": 11742.9,
      "health_govt": 2239.55,
      "overseas_medical": 3.12,
      "health_total": 16682.64,
      "basis": "as printed in the report",
      "source_basis": "prior-year comparative columns",
      "period_label": "For the period up to March 2023",
      "provenance": {
        "source_name": "GI Council Segment-wise Report (upto March 2024 (FY24, provisional & unaudited)) — prior-year comparative columns",
        "source_url": "https://www.gicouncil.in/media/4418/segment_march_2024-16.xlsx",
        "source_file": "data/agent-pulls/gicouncil-segment/sources/segment_march_2024-16.xlsx",
        "source_period": "FY23",
        "fetched_at": "2026-06-10T17:04:18.008Z",
        "parsed_at": "2026-06-10T17:04:18.200Z",
        "parser_name": "ingest-gicouncil-segment-annual",
        "confidence": "high"
      }
    },
    {
      "fiscal_year": "FY23",
      "entity": "oriental-insurance",
      "carrier_group": "general",
      "insurer_name": "The Oriental Insurance Co Ltd",
      "health_retail": 1738.68,
      "health_group": 4461.44,
      "health_govt": 2008.1,
      "overseas_medical": 4.18,
      "health_total": 8212.4,
      "basis": "as printed in the report",
      "source_basis": "prior-year comparative columns",
      "period_label": "For the period up to March 2023",
      "provenance": {
        "source_name": "GI Council Segment-wise Report (upto March 2024 (FY24, provisional & unaudited)) — prior-year comparative columns",
        "source_url": "https://www.gicouncil.in/media/4418/segment_march_2024-16.xlsx",
        "source_file": "data/agent-pulls/gicouncil-segment/sources/segment_march_2024-16.xlsx",
        "source_period": "FY23",
        "fetched_at": "2026-06-10T17:04:18.008Z",
        "parsed_at": "2026-06-10T17:04:18.200Z",
        "parser_name": "ingest-gicouncil-segment-annual",
        "confidence": "high"
      }
    },
    {
      "fiscal_year": "FY23",
      "entity": "united-india",
      "carrier_group": "general",
      "insurer_name": "United India Insurance Co Ltd",
      "health_retail": 1382.21,
      "health_group": 3014.04,
      "health_govt": 2847.5,
      "overseas_medical": 4.47,
      "health_total": 7248.22,
      "basis": "as printed in the report",
      "source_basis": "prior-year comparative columns",
      "period_label": "For the period up to March 2023",
      "provenance": {
        "source_name": "GI Council Segment-wise Report (upto March 2024 (FY24, provisional & unaudited)) — prior-year comparative columns",
        "source_url": "https://www.gicouncil.in/media/4418/segment_march_2024-16.xlsx",
        "source_file": "data/agent-pulls/gicouncil-segment/sources/segment_march_2024-16.xlsx",
        "source_period": "FY23",
        "fetched_at": "2026-06-10T17:04:18.008Z",
        "parsed_at": "2026-06-10T17:04:18.200Z",
        "parser_name": "ingest-gicouncil-segment-annual",
        "confidence": "high"
      }
    },
    {
      "fiscal_year": "FY23",
      "entity": "niva-bupa",
      "carrier_group": "sahi",
      "insurer_name": "Niva bupa health insurance company limited",
      "health_retail": 2969.74,
      "health_group": 1017.62,
      "health_govt": 0,
      "overseas_medical": 5.63,
      "health_total": 3992.99,
      "basis": "as printed in the report",
      "source_basis": "prior-year comparative columns",
      "period_label": "For the period up to March 2023",
      "provenance": {
        "source_name": "GI Council Segment-wise Report (upto March 2024 (FY24, provisional & unaudited)) — prior-year comparative columns",
        "source_url": "https://www.gicouncil.in/media/4418/segment_march_2024-16.xlsx",
        "source_file": "data/agent-pulls/gicouncil-segment/sources/segment_march_2024-16.xlsx",
        "source_period": "FY23",
        "fetched_at": "2026-06-10T17:04:18.008Z",
        "parsed_at": "2026-06-10T17:04:18.200Z",
        "parser_name": "ingest-gicouncil-segment-annual",
        "confidence": "high"
      }
    },
    {
      "fiscal_year": "FY23",
      "entity": "aditya-birla",
      "carrier_group": "sahi",
      "insurer_name": "Aditya Birla Health Insurance Co Ltd",
      "health_retail": 835.36,
      "health_group": 1647.35,
      "health_govt": 0,
      "overseas_medical": 74.11,
      "health_total": 2556.82,
      "basis": "as printed in the report",
      "source_basis": "prior-year comparative columns",
      "period_label": "For the period up to March 2023",
      "provenance": {
        "source_name": "GI Council Segment-wise Report (upto March 2024 (FY24, provisional & unaudited)) — prior-year comparative columns",
        "source_url": "https://www.gicouncil.in/media/4418/segment_march_2024-16.xlsx",
        "source_file": "data/agent-pulls/gicouncil-segment/sources/segment_march_2024-16.xlsx",
        "source_period": "FY23",
        "fetched_at": "2026-06-10T17:04:18.008Z",
        "parsed_at": "2026-06-10T17:04:18.200Z",
        "parser_name": "ingest-gicouncil-segment-annual",
        "confidence": "high"
      }
    },
    {
      "fiscal_year": "FY23",
      "entity": "care-health",
      "carrier_group": "sahi",
      "insurer_name": "Care Health Insurance Ltd",
      "health_retail": 2727.7,
      "health_group": 1969.94,
      "health_govt": 0,
      "overseas_medical": 122.26,
      "health_total": 4819.9,
      "basis": "as printed in the report",
      "source_basis": "prior-year comparative columns",
      "period_label": "For the period up to March 2023",
      "provenance": {
        "source_name": "GI Council Segment-wise Report (upto March 2024 (FY24, provisional & unaudited)) — prior-year comparative columns",
        "source_url": "https://www.gicouncil.in/media/4418/segment_march_2024-16.xlsx",
        "source_file": "data/agent-pulls/gicouncil-segment/sources/segment_march_2024-16.xlsx",
        "source_period": "FY23",
        "fetched_at": "2026-06-10T17:04:18.008Z",
        "parsed_at": "2026-06-10T17:04:18.200Z",
        "parser_name": "ingest-gicouncil-segment-annual",
        "confidence": "high"
      }
    },
    {
      "fiscal_year": "FY23",
      "entity": "manipalcigna",
      "carrier_group": "sahi",
      "insurer_name": "ManipalCigna Health Insurance Co Ltd",
      "health_retail": 578.57,
      "health_group": 748.78,
      "health_govt": 0,
      "overseas_medical": 1.59,
      "health_total": 1328.94,
      "basis": "as printed in the report",
      "source_basis": "prior-year comparative columns",
      "period_label": "For the period up to March 2023",
      "provenance": {
        "source_name": "GI Council Segment-wise Report (upto March 2024 (FY24, provisional & unaudited)) — prior-year comparative columns",
        "source_url": "https://www.gicouncil.in/media/4418/segment_march_2024-16.xlsx",
        "source_file": "data/agent-pulls/gicouncil-segment/sources/segment_march_2024-16.xlsx",
        "source_period": "FY23",
        "fetched_at": "2026-06-10T17:04:18.008Z",
        "parsed_at": "2026-06-10T17:04:18.200Z",
        "parser_name": "ingest-gicouncil-segment-annual",
        "confidence": "high"
      }
    },
    {
      "fiscal_year": "FY23",
      "entity": "star-health",
      "carrier_group": "sahi",
      "insurer_name": "Star Health & Allied Insurance Co Ltd",
      "health_retail": 11950.3,
      "health_group": 806.31,
      "health_govt": 0,
      "overseas_medical": 2.02,
      "health_total": 12758.63,
      "basis": "as printed in the report",
      "source_basis": "prior-year comparative columns",
      "period_label": "For the period up to March 2023",
      "provenance": {
        "source_name": "GI Council Segment-wise Report (upto March 2024 (FY24, provisional & unaudited)) — prior-year comparative columns",
        "source_url": "https://www.gicouncil.in/media/4418/segment_march_2024-16.xlsx",
        "source_file": "data/agent-pulls/gicouncil-segment/sources/segment_march_2024-16.xlsx",
        "source_period": "FY23",
        "fetched_at": "2026-06-10T17:04:18.008Z",
        "parsed_at": "2026-06-10T17:04:18.200Z",
        "parser_name": "ingest-gicouncil-segment-annual",
        "confidence": "high"
      }
    },
    {
      "fiscal_year": "FY23",
      "entity": "GENERAL",
      "carrier_group": "aggregate",
      "insurer_name": "General Insurers Sub Total (as printed)",
      "health_retail": 16368.35,
      "health_group": 39460.06,
      "health_govt": 8496.22,
      "overseas_medical": 869.73,
      "health_total": 65194.36,
      "basis": "as printed in the report",
      "source_basis": "prior-year comparative columns",
      "period_label": "For the period up to March 2023",
      "provenance": {
        "source_name": "GI Council Segment-wise Report (upto March 2024 (FY24, provisional & unaudited)) — prior-year comparative columns",
        "source_url": "https://www.gicouncil.in/media/4418/segment_march_2024-16.xlsx",
        "source_file": "data/agent-pulls/gicouncil-segment/sources/segment_march_2024-16.xlsx",
        "source_period": "FY23",
        "fetched_at": "2026-06-10T17:07:57.519Z",
        "parsed_at": "2026-06-10T17:07:57.708Z",
        "parser_name": "ingest-gicouncil-segment-annual",
        "confidence": "high"
      }
    },
    {
      "fiscal_year": "FY23",
      "entity": "SAHI",
      "carrier_group": "aggregate",
      "insurer_name": "Stand-alone Health sub Total (as printed)",
      "health_retail": 19061.67,
      "health_group": 6190,
      "health_govt": 0,
      "overseas_medical": 205.61,
      "health_total": 25457.28,
      "basis": "as printed in the report",
      "source_basis": "prior-year comparative columns",
      "period_label": "For the period up to March 2023",
      "provenance": {
        "source_name": "GI Council Segment-wise Report (upto March 2024 (FY24, provisional & unaudited)) — prior-year comparative columns",
        "source_url": "https://www.gicouncil.in/media/4418/segment_march_2024-16.xlsx",
        "source_file": "data/agent-pulls/gicouncil-segment/sources/segment_march_2024-16.xlsx",
        "source_period": "FY23",
        "fetched_at": "2026-06-10T17:04:18.008Z",
        "parsed_at": "2026-06-10T17:04:18.200Z",
        "parser_name": "ingest-gicouncil-segment-annual",
        "confidence": "high"
      }
    },
    {
      "fiscal_year": "FY23",
      "entity": "INDUSTRY",
      "carrier_group": "aggregate",
      "insurer_name": "Industry Total (as printed)",
      "health_retail": 35430.02,
      "health_group": 45650.06,
      "health_govt": 8496.22,
      "overseas_medical": 1075.34,
      "health_total": 90651.64,
      "basis": "as printed in the report",
      "source_basis": "prior-year comparative columns",
      "period_label": "For the period up to March 2023",
      "provenance": {
        "source_name": "GI Council Segment-wise Report (upto March 2024 (FY24, provisional & unaudited)) — prior-year comparative columns",
        "source_url": "https://www.gicouncil.in/media/4418/segment_march_2024-16.xlsx",
        "source_file": "data/agent-pulls/gicouncil-segment/sources/segment_march_2024-16.xlsx",
        "source_period": "FY23",
        "fetched_at": "2026-06-10T17:07:57.519Z",
        "parsed_at": "2026-06-10T17:07:57.708Z",
        "parser_name": "ingest-gicouncil-segment-annual",
        "confidence": "high"
      }
    },
    {
      "fiscal_year": "FY23",
      "entity": "PSUs",
      "carrier_group": "aggregate",
      "insurer_name": "Public-sector general insurers",
      "health_retail": 7999.97,
      "health_group": 23098.26,
      "health_govt": 7964.79,
      "overseas_medical": 15.09,
      "health_total": 39078.11,
      "basis": "derived: sum of the printed National + New India + Oriental + United India rows",
      "source_basis": "prior-year comparative columns",
      "period_label": "For the period up to March 2023",
      "provenance": {
        "source_name": "GI Council Segment-wise Report (upto March 2024 (FY24, provisional & unaudited)) — prior-year comparative columns",
        "source_url": "https://www.gicouncil.in/media/4418/segment_march_2024-16.xlsx",
        "source_file": "data/agent-pulls/gicouncil-segment/sources/segment_march_2024-16.xlsx",
        "source_period": "FY23",
        "fetched_at": "2026-06-10T17:04:18.008Z",
        "parsed_at": "2026-06-10T17:04:18.200Z",
        "parser_name": "ingest-gicouncil-segment-annual",
        "confidence": "high"
      }
    },
    {
      "fiscal_year": "FY23",
      "entity": "Private",
      "carrier_group": "aggregate",
      "insurer_name": "Private general insurers",
      "health_retail": 8368.38,
      "health_group": 16361.8,
      "health_govt": 531.43,
      "overseas_medical": 854.64,
      "health_total": 26116.25,
      "basis": "derived: printed General Insurers Sub Total − the 4 public-sector insurers",
      "source_basis": "prior-year comparative columns",
      "period_label": "For the period up to March 2023",
      "provenance": {
        "source_name": "GI Council Segment-wise Report (upto March 2024 (FY24, provisional & unaudited)) — prior-year comparative columns",
        "source_url": "https://www.gicouncil.in/media/4418/segment_march_2024-16.xlsx",
        "source_file": "data/agent-pulls/gicouncil-segment/sources/segment_march_2024-16.xlsx",
        "source_period": "FY23",
        "fetched_at": "2026-06-10T17:04:18.008Z",
        "parsed_at": "2026-06-10T17:04:18.200Z",
        "parser_name": "ingest-gicouncil-segment-annual",
        "confidence": "high"
      }
    },
    {
      "fiscal_year": "FY23",
      "entity": "Others",
      "carrier_group": "aggregate",
      "insurer_name": "All other insurers (retail health)",
      "health_retail": 3890.68,
      "health_group": null,
      "health_govt": null,
      "overseas_medical": null,
      "health_total": null,
      "basis": "derived: printed Industry Total retail − the 11 named insurer rows",
      "source_basis": "prior-year comparative columns",
      "period_label": "For the period up to March 2023",
      "provenance": {
        "source_name": "GI Council Segment-wise Report (upto March 2024 (FY24, provisional & unaudited)) — prior-year comparative columns",
        "source_url": "https://www.gicouncil.in/media/4418/segment_march_2024-16.xlsx",
        "source_file": "data/agent-pulls/gicouncil-segment/sources/segment_march_2024-16.xlsx",
        "source_period": "FY23",
        "fetched_at": "2026-06-10T17:04:18.008Z",
        "parsed_at": "2026-06-10T17:04:18.200Z",
        "parser_name": "ingest-gicouncil-segment-annual",
        "confidence": "high"
      }
    },
    {
      "fiscal_year": "FY24",
      "entity": "hdfc-ergo",
      "carrier_group": "general",
      "insurer_name": "HDFC Ergo General Insurance Co Ltd",
      "health_retail": 3964.17,
      "health_group": 1977.83,
      "health_govt": 0,
      "overseas_medical": 32.86,
      "health_total": 5974.86,
      "basis": "as printed in the report",
      "source_basis": "prior-year comparative columns",
      "period_label": "For the period up to March 2024",
      "provenance": {
        "source_name": "GI Council Segment-wise Report (upto March 2025 (FY25, final)) — prior-year comparative columns",
        "source_url": "https://www.gicouncil.in/media/4513/final-segment-24-25.xlsx",
        "source_file": "data/agent-pulls/gicouncil-segment/sources/final-segment-24-25.xlsx",
        "source_period": "FY24",
        "fetched_at": "2026-06-10T17:08:07.151Z",
        "parsed_at": "2026-06-10T17:08:07.352Z",
        "parser_name": "ingest-gicouncil-segment-annual",
        "confidence": "high"
      }
    },
    {
      "fiscal_year": "FY24",
      "entity": "icici-lombard",
      "carrier_group": "general",
      "insurer_name": "ICICI Lombard General Insurance Co Ltd",
      "health_retail": 1244.52,
      "health_group": 4926.65,
      "health_govt": 0,
      "overseas_medical": 230.02,
      "health_total": 6401.19,
      "basis": "as printed in the report",
      "source_basis": "prior-year comparative columns",
      "period_label": "For the period up to March 2024",
      "provenance": {
        "source_name": "GI Council Segment-wise Report (upto March 2025 (FY25, final)) — prior-year comparative columns",
        "source_url": "https://www.gicouncil.in/media/4513/final-segment-24-25.xlsx",
        "source_file": "data/agent-pulls/gicouncil-segment/sources/final-segment-24-25.xlsx",
        "source_period": "FY24",
        "fetched_at": "2026-06-10T17:08:07.151Z",
        "parsed_at": "2026-06-10T17:08:07.352Z",
        "parser_name": "ingest-gicouncil-segment-annual",
        "confidence": "high"
      }
    },
    {
      "fiscal_year": "FY24",
      "entity": "national-insurance",
      "carrier_group": "general",
      "insurer_name": "National Insurance Co Ltd",
      "health_retail": 2332.59,
      "health_group": 4098,
      "health_govt": 495.44,
      "overseas_medical": 3.28,
      "health_total": 6929.31,
      "basis": "as printed in the report",
      "source_basis": "prior-year comparative columns",
      "period_label": "For the period up to March 2024",
      "provenance": {
        "source_name": "GI Council Segment-wise Report (upto March 2025 (FY25, final)) — prior-year comparative columns",
        "source_url": "https://www.gicouncil.in/media/4513/final-segment-24-25.xlsx",
        "source_file": "data/agent-pulls/gicouncil-segment/sources/final-segment-24-25.xlsx",
        "source_period": "FY24",
        "fetched_at": "2026-06-10T17:08:07.151Z",
        "parsed_at": "2026-06-10T17:08:07.352Z",
        "parser_name": "ingest-gicouncil-segment-annual",
        "confidence": "high"
      }
    },
    {
      "fiscal_year": "FY24",
      "entity": "new-india",
      "carrier_group": "general",
      "insurer_name": "The New India Assurance Co Ltd",
      "health_retail": 3098.81,
      "health_group": 12424.1,
      "health_govt": 2790.54,
      "overseas_medical": 7.2,
      "health_total": 18320.65,
      "basis": "as printed in the report",
      "source_basis": "prior-year comparative columns",
      "period_label": "For the period up to March 2024",
      "provenance": {
        "source_name": "GI Council Segment-wise Report (upto March 2025 (FY25, final)) — prior-year comparative columns",
        "source_url": "https://www.gicouncil.in/media/4513/final-segment-24-25.xlsx",
        "source_file": "data/agent-pulls/gicouncil-segment/sources/final-segment-24-25.xlsx",
        "source_period": "FY24",
        "fetched_at": "2026-06-10T17:08:07.151Z",
        "parsed_at": "2026-06-10T17:08:07.352Z",
        "parser_name": "ingest-gicouncil-segment-annual",
        "confidence": "high"
      }
    },
    {
      "fiscal_year": "FY24",
      "entity": "oriental-insurance",
      "carrier_group": "general",
      "insurer_name": "The Oriental Insurance Co Ltd",
      "health_retail": 1786.91,
      "health_group": 5228.71,
      "health_govt": 845.24,
      "overseas_medical": 4.21,
      "health_total": 7865.07,
      "basis": "as printed in the report",
      "source_basis": "prior-year comparative columns",
      "period_label": "For the period up to March 2024",
      "provenance": {
        "source_name": "GI Council Segment-wise Report (upto March 2025 (FY25, final)) — prior-year comparative columns",
        "source_url": "https://www.gicouncil.in/media/4513/final-segment-24-25.xlsx",
        "source_file": "data/agent-pulls/gicouncil-segment/sources/final-segment-24-25.xlsx",
        "source_period": "FY24",
        "fetched_at": "2026-06-10T17:08:07.151Z",
        "parsed_at": "2026-06-10T17:08:07.352Z",
        "parser_name": "ingest-gicouncil-segment-annual",
        "confidence": "high"
      }
    },
    {
      "fiscal_year": "FY24",
      "entity": "united-india",
      "carrier_group": "general",
      "insurer_name": "United India Insurance Co Ltd",
      "health_retail": 1561.6,
      "health_group": 3354.04,
      "health_govt": 2976.99,
      "overseas_medical": 4.36,
      "health_total": 7896.99,
      "basis": "as printed in the report",
      "source_basis": "prior-year comparative columns",
      "period_label": "For the period up to March 2024",
      "provenance": {
        "source_name": "GI Council Segment-wise Report (upto March 2025 (FY25, final)) — prior-year comparative columns",
        "source_url": "https://www.gicouncil.in/media/4513/final-segment-24-25.xlsx",
        "source_file": "data/agent-pulls/gicouncil-segment/sources/final-segment-24-25.xlsx",
        "source_period": "FY24",
        "fetched_at": "2026-06-10T17:08:07.151Z",
        "parsed_at": "2026-06-10T17:08:07.352Z",
        "parser_name": "ingest-gicouncil-segment-annual",
        "confidence": "high"
      }
    },
    {
      "fiscal_year": "FY24",
      "entity": "niva-bupa",
      "carrier_group": "sahi",
      "insurer_name": "Niva bupa health insurance company limited",
      "health_retail": 3839.73,
      "health_group": 1654.69,
      "health_govt": 0,
      "overseas_medical": 20.47,
      "health_total": 5514.89,
      "basis": "as printed in the report",
      "source_basis": "prior-year comparative columns",
      "period_label": "For the period up to March 2024",
      "provenance": {
        "source_name": "GI Council Segment-wise Report (upto March 2025 (FY25, final)) — prior-year comparative columns",
        "source_url": "https://www.gicouncil.in/media/4513/final-segment-24-25.xlsx",
        "source_file": "data/agent-pulls/gicouncil-segment/sources/final-segment-24-25.xlsx",
        "source_period": "FY24",
        "fetched_at": "2026-06-10T17:08:07.151Z",
        "parsed_at": "2026-06-10T17:08:07.352Z",
        "parser_name": "ingest-gicouncil-segment-annual",
        "confidence": "high"
      }
    },
    {
      "fiscal_year": "FY24",
      "entity": "aditya-birla",
      "carrier_group": "sahi",
      "insurer_name": "Aditya Birla Health Insurance Co Ltd",
      "health_retail": 1127.23,
      "health_group": 2319.92,
      "health_govt": 0,
      "overseas_medical": 33.69,
      "health_total": 3480.84,
      "basis": "as printed in the report",
      "source_basis": "prior-year comparative columns",
      "period_label": "For the period up to March 2024",
      "provenance": {
        "source_name": "GI Council Segment-wise Report (upto March 2025 (FY25, final)) — prior-year comparative columns",
        "source_url": "https://www.gicouncil.in/media/4513/final-segment-24-25.xlsx",
        "source_file": "data/agent-pulls/gicouncil-segment/sources/final-segment-24-25.xlsx",
        "source_period": "FY24",
        "fetched_at": "2026-06-10T17:08:07.151Z",
        "parsed_at": "2026-06-10T17:08:07.352Z",
        "parser_name": "ingest-gicouncil-segment-annual",
        "confidence": "high"
      }
    },
    {
      "fiscal_year": "FY24",
      "entity": "care-health",
      "carrier_group": "sahi",
      "insurer_name": "Care Health Insurance Ltd",
      "health_retail": 3973.83,
      "health_group": 2571.75,
      "health_govt": 0,
      "overseas_medical": 112.05,
      "health_total": 6657.63,
      "basis": "as printed in the report",
      "source_basis": "prior-year comparative columns",
      "period_label": "For the period up to March 2024",
      "provenance": {
        "source_name": "GI Council Segment-wise Report (upto March 2025 (FY25, final)) — prior-year comparative columns",
        "source_url": "https://www.gicouncil.in/media/4513/final-segment-24-25.xlsx",
        "source_file": "data/agent-pulls/gicouncil-segment/sources/final-segment-24-25.xlsx",
        "source_period": "FY24",
        "fetched_at": "2026-06-10T17:08:07.151Z",
        "parsed_at": "2026-06-10T17:08:07.352Z",
        "parser_name": "ingest-gicouncil-segment-annual",
        "confidence": "high"
      }
    },
    {
      "fiscal_year": "FY24",
      "entity": "manipalcigna",
      "carrier_group": "sahi",
      "insurer_name": "ManipalCigna Health Insurance Co Ltd",
      "health_retail": 746.08,
      "health_group": 909.84,
      "health_govt": 0,
      "overseas_medical": 2.26,
      "health_total": 1658.18,
      "basis": "as printed in the report",
      "source_basis": "prior-year comparative columns",
      "period_label": "For the period up to March 2024",
      "provenance": {
        "source_name": "GI Council Segment-wise Report (upto March 2025 (FY25, final)) — prior-year comparative columns",
        "source_url": "https://www.gicouncil.in/media/4513/final-segment-24-25.xlsx",
        "source_file": "data/agent-pulls/gicouncil-segment/sources/final-segment-24-25.xlsx",
        "source_period": "FY24",
        "fetched_at": "2026-06-10T17:08:07.151Z",
        "parsed_at": "2026-06-10T17:08:07.352Z",
        "parser_name": "ingest-gicouncil-segment-annual",
        "confidence": "high"
      }
    },
    {
      "fiscal_year": "FY24",
      "entity": "star-health",
      "carrier_group": "sahi",
      "insurer_name": "Star Health & Allied Insurance Co Ltd",
      "health_retail": 13951.3,
      "health_group": 1085.67,
      "health_govt": 0,
      "overseas_medical": 5.71,
      "health_total": 15042.68,
      "basis": "as printed in the report",
      "source_basis": "prior-year comparative columns",
      "period_label": "For the period up to March 2024",
      "provenance": {
        "source_name": "GI Council Segment-wise Report (upto March 2025 (FY25, final)) — prior-year comparative columns",
        "source_url": "https://www.gicouncil.in/media/4513/final-segment-24-25.xlsx",
        "source_file": "data/agent-pulls/gicouncil-segment/sources/final-segment-24-25.xlsx",
        "source_period": "FY24",
        "fetched_at": "2026-06-10T17:08:07.151Z",
        "parsed_at": "2026-06-10T17:08:07.352Z",
        "parser_name": "ingest-gicouncil-segment-annual",
        "confidence": "high"
      }
    },
    {
      "fiscal_year": "FY24",
      "entity": "GENERAL",
      "carrier_group": "aggregate",
      "insurer_name": "General Insurers Sub Total (as printed)",
      "health_retail": 18530.81,
      "health_group": 46478.12,
      "health_govt": 10513.67,
      "overseas_medical": 1034.57,
      "health_total": 76557.17,
      "basis": "as printed in the report",
      "source_basis": "prior-year comparative columns",
      "period_label": "For the period up to March 2024",
      "provenance": {
        "source_name": "GI Council Segment-wise Report (upto March 2025 (FY25, final)) — prior-year comparative columns",
        "source_url": "https://www.gicouncil.in/media/4513/final-segment-24-25.xlsx",
        "source_file": "data/agent-pulls/gicouncil-segment/sources/final-segment-24-25.xlsx",
        "source_period": "FY24",
        "fetched_at": "2026-06-10T17:08:07.151Z",
        "parsed_at": "2026-06-10T17:08:07.352Z",
        "parser_name": "ingest-gicouncil-segment-annual",
        "confidence": "high"
      }
    },
    {
      "fiscal_year": "FY24",
      "entity": "SAHI",
      "carrier_group": "aggregate",
      "insurer_name": "Stand-alone Health sub Total (as printed)",
      "health_retail": 23638.17,
      "health_group": 8541.87,
      "health_govt": 0,
      "overseas_medical": 174.18,
      "health_total": 32354.22,
      "basis": "as printed in the report",
      "source_basis": "prior-year comparative columns",
      "period_label": "For the period up to March 2024",
      "provenance": {
        "source_name": "GI Council Segment-wise Report (upto March 2025 (FY25, final)) — prior-year comparative columns",
        "source_url": "https://www.gicouncil.in/media/4513/final-segment-24-25.xlsx",
        "source_file": "data/agent-pulls/gicouncil-segment/sources/final-segment-24-25.xlsx",
        "source_period": "FY24",
        "fetched_at": "2026-06-10T17:08:07.151Z",
        "parsed_at": "2026-06-10T17:08:07.352Z",
        "parser_name": "ingest-gicouncil-segment-annual",
        "confidence": "high"
      }
    },
    {
      "fiscal_year": "FY24",
      "entity": "INDUSTRY",
      "carrier_group": "aggregate",
      "insurer_name": "Industry Total (as printed)",
      "health_retail": 42168.98,
      "health_group": 55019.99,
      "health_govt": 10513.67,
      "overseas_medical": 1208.75,
      "health_total": 108911.39,
      "basis": "as printed in the report",
      "source_basis": "prior-year comparative columns",
      "period_label": "For the period up to March 2024",
      "provenance": {
        "source_name": "GI Council Segment-wise Report (upto March 2025 (FY25, final)) — prior-year comparative columns",
        "source_url": "https://www.gicouncil.in/media/4513/final-segment-24-25.xlsx",
        "source_file": "data/agent-pulls/gicouncil-segment/sources/final-segment-24-25.xlsx",
        "source_period": "FY24",
        "fetched_at": "2026-06-10T17:08:07.151Z",
        "parsed_at": "2026-06-10T17:08:07.352Z",
        "parser_name": "ingest-gicouncil-segment-annual",
        "confidence": "high"
      }
    },
    {
      "fiscal_year": "FY24",
      "entity": "PSUs",
      "carrier_group": "aggregate",
      "insurer_name": "Public-sector general insurers",
      "health_retail": 8779.91,
      "health_group": 25104.85,
      "health_govt": 7108.21,
      "overseas_medical": 19.05,
      "health_total": 41012.02,
      "basis": "derived: sum of the printed National + New India + Oriental + United India rows",
      "source_basis": "prior-year comparative columns",
      "period_label": "For the period up to March 2024",
      "provenance": {
        "source_name": "GI Council Segment-wise Report (upto March 2025 (FY25, final)) — prior-year comparative columns",
        "source_url": "https://www.gicouncil.in/media/4513/final-segment-24-25.xlsx",
        "source_file": "data/agent-pulls/gicouncil-segment/sources/final-segment-24-25.xlsx",
        "source_period": "FY24",
        "fetched_at": "2026-06-10T17:08:07.151Z",
        "parsed_at": "2026-06-10T17:08:07.352Z",
        "parser_name": "ingest-gicouncil-segment-annual",
        "confidence": "high"
      }
    },
    {
      "fiscal_year": "FY24",
      "entity": "Private",
      "carrier_group": "aggregate",
      "insurer_name": "Private general insurers",
      "health_retail": 9750.9,
      "health_group": 21373.27,
      "health_govt": 3405.46,
      "overseas_medical": 1015.52,
      "health_total": 35545.15,
      "basis": "derived: printed General Insurers Sub Total − the 4 public-sector insurers",
      "source_basis": "prior-year comparative columns",
      "period_label": "For the period up to March 2024",
      "provenance": {
        "source_name": "GI Council Segment-wise Report (upto March 2025 (FY25, final)) — prior-year comparative columns",
        "source_url": "https://www.gicouncil.in/media/4513/final-segment-24-25.xlsx",
        "source_file": "data/agent-pulls/gicouncil-segment/sources/final-segment-24-25.xlsx",
        "source_period": "FY24",
        "fetched_at": "2026-06-10T17:08:07.151Z",
        "parsed_at": "2026-06-10T17:08:07.352Z",
        "parser_name": "ingest-gicouncil-segment-annual",
        "confidence": "high"
      }
    },
    {
      "fiscal_year": "FY24",
      "entity": "Others",
      "carrier_group": "aggregate",
      "insurer_name": "All other insurers (retail health)",
      "health_retail": 4542.21,
      "health_group": null,
      "health_govt": null,
      "overseas_medical": null,
      "health_total": null,
      "basis": "derived: printed Industry Total retail − the 11 named insurer rows",
      "source_basis": "prior-year comparative columns",
      "period_label": "For the period up to March 2024",
      "provenance": {
        "source_name": "GI Council Segment-wise Report (upto March 2025 (FY25, final)) — prior-year comparative columns",
        "source_url": "https://www.gicouncil.in/media/4513/final-segment-24-25.xlsx",
        "source_file": "data/agent-pulls/gicouncil-segment/sources/final-segment-24-25.xlsx",
        "source_period": "FY24",
        "fetched_at": "2026-06-10T17:08:07.151Z",
        "parsed_at": "2026-06-10T17:08:07.352Z",
        "parser_name": "ingest-gicouncil-segment-annual",
        "confidence": "high"
      }
    },
    {
      "fiscal_year": "FY24",
      "entity": "galaxy-health",
      "carrier_group": "sahi",
      "insurer_name": "Galaxy Health Insurance Company Ltd",
      "health_retail": 0,
      "health_group": 0,
      "health_govt": 0,
      "overseas_medical": 0,
      "health_total": 0,
      "basis": "as printed in the report",
      "source_basis": "prior-year comparative columns",
      "period_label": "For the period up to March 2024",
      "provenance": {
        "source_name": "GI Council Segment-wise Report (upto March 2025 (FY25, final)) — prior-year comparative columns",
        "source_url": "https://www.gicouncil.in/media/4513/final-segment-24-25.xlsx",
        "source_file": "data/agent-pulls/gicouncil-segment/sources/final-segment-24-25.xlsx",
        "source_period": "FY24",
        "fetched_at": "2026-06-10T17:04:18.008Z",
        "parsed_at": "2026-06-10T17:04:18.201Z",
        "parser_name": "ingest-gicouncil-segment-annual",
        "confidence": "high"
      }
    },
    {
      "fiscal_year": "FY24",
      "entity": "narayana-health",
      "carrier_group": "sahi",
      "insurer_name": "Narayana Health Insurance Ltd",
      "health_retail": 0,
      "health_group": 0,
      "health_govt": 0,
      "overseas_medical": 0,
      "health_total": 0,
      "basis": "as printed in the report",
      "source_basis": "prior-year comparative columns",
      "period_label": "For the period up to March 2024",
      "provenance": {
        "source_name": "GI Council Segment-wise Report (upto March 2025 (FY25, final)) — prior-year comparative columns",
        "source_url": "https://www.gicouncil.in/media/4513/final-segment-24-25.xlsx",
        "source_file": "data/agent-pulls/gicouncil-segment/sources/final-segment-24-25.xlsx",
        "source_period": "FY24",
        "fetched_at": "2026-06-10T17:04:18.008Z",
        "parsed_at": "2026-06-10T17:04:18.201Z",
        "parser_name": "ingest-gicouncil-segment-annual",
        "confidence": "high"
      }
    },
    {
      "fiscal_year": "FY25",
      "entity": "hdfc-ergo",
      "carrier_group": "general",
      "insurer_name": "HDFC Ergo General Insurance Co Ltd",
      "health_retail": 4212.7,
      "health_group": 1507.05,
      "health_govt": 0,
      "overseas_medical": 33.35,
      "health_total": 5753.1,
      "basis": "as printed in the report",
      "source_basis": "prior-year comparative columns",
      "period_label": "For the period up to March 2025",
      "provenance": {
        "source_name": "GI Council Segment-wise Report (upto March 2026 (FY26, provisional & unaudited)) — prior-year comparative columns",
        "source_url": "https://www.gicouncil.in/media/4638/segment_march_2026-170426.xlsx",
        "source_file": "data/agent-pulls/industry-segment-history/sources/segment_march_2026-170426.xlsx",
        "source_period": "FY25",
        "fetched_at": "2026-06-10T17:08:07.151Z",
        "parsed_at": "2026-06-10T17:08:07.353Z",
        "parser_name": "ingest-gicouncil-segment-annual",
        "confidence": "high"
      }
    },
    {
      "fiscal_year": "FY25",
      "entity": "icici-lombard",
      "carrier_group": "general",
      "insurer_name": "ICICI Lombard General Insurance Co Ltd",
      "health_retail": 1556.23,
      "health_group": 5393.8,
      "health_govt": 0,
      "overseas_medical": 238.27,
      "health_total": 7188.3,
      "basis": "as printed in the report",
      "source_basis": "prior-year comparative columns",
      "period_label": "For the period up to March 2025",
      "provenance": {
        "source_name": "GI Council Segment-wise Report (upto March 2026 (FY26, provisional & unaudited)) — prior-year comparative columns",
        "source_url": "https://www.gicouncil.in/media/4638/segment_march_2026-170426.xlsx",
        "source_file": "data/agent-pulls/industry-segment-history/sources/segment_march_2026-170426.xlsx",
        "source_period": "FY25",
        "fetched_at": "2026-06-10T17:08:07.151Z",
        "parsed_at": "2026-06-10T17:08:07.353Z",
        "parser_name": "ingest-gicouncil-segment-annual",
        "confidence": "high"
      }
    },
    {
      "fiscal_year": "FY25",
      "entity": "national-insurance",
      "carrier_group": "general",
      "insurer_name": "National Insurance Co Ltd",
      "health_retail": 2443.34,
      "health_group": 4792.18,
      "health_govt": 727.75,
      "overseas_medical": 4.25,
      "health_total": 7967.52,
      "basis": "as printed in the report",
      "source_basis": "prior-year comparative columns",
      "period_label": "For the period up to March 2025",
      "provenance": {
        "source_name": "GI Council Segment-wise Report (upto March 2026 (FY26, provisional & unaudited)) — prior-year comparative columns",
        "source_url": "https://www.gicouncil.in/media/4638/segment_march_2026-170426.xlsx",
        "source_file": "data/agent-pulls/industry-segment-history/sources/segment_march_2026-170426.xlsx",
        "source_period": "FY25",
        "fetched_at": "2026-06-10T17:08:07.151Z",
        "parsed_at": "2026-06-10T17:08:07.353Z",
        "parser_name": "ingest-gicouncil-segment-annual",
        "confidence": "high"
      }
    },
    {
      "fiscal_year": "FY25",
      "entity": "new-india",
      "carrier_group": "general",
      "insurer_name": "The New India Assurance Co Ltd",
      "health_retail": 3422.78,
      "health_group": 12996.3,
      "health_govt": 2768.83,
      "overseas_medical": 6.78,
      "health_total": 19194.69,
      "basis": "as printed in the report",
      "source_basis": "prior-year comparative columns",
      "period_label": "For the period up to March 2025",
      "provenance": {
        "source_name": "GI Council Segment-wise Report (upto March 2026 (FY26, provisional & unaudited)) — prior-year comparative columns",
        "source_url": "https://www.gicouncil.in/media/4638/segment_march_2026-170426.xlsx",
        "source_file": "data/agent-pulls/industry-segment-history/sources/segment_march_2026-170426.xlsx",
        "source_period": "FY25",
        "fetched_at": "2026-06-10T17:08:07.151Z",
        "parsed_at": "2026-06-10T17:08:07.353Z",
        "parser_name": "ingest-gicouncil-segment-annual",
        "confidence": "high"
      }
    },
    {
      "fiscal_year": "FY25",
      "entity": "oriental-insurance",
      "carrier_group": "general",
      "insurer_name": "The Oriental Insurance Co Ltd",
      "health_retail": 1859.21,
      "health_group": 5801.55,
      "health_govt": 578.49,
      "overseas_medical": 3.62,
      "health_total": 8242.87,
      "basis": "as printed in the report",
      "source_basis": "prior-year comparative columns",
      "period_label": "For the period up to March 2025",
      "provenance": {
        "source_name": "GI Council Segment-wise Report (upto March 2026 (FY26, provisional & unaudited)) — prior-year comparative columns",
        "source_url": "https://www.gicouncil.in/media/4638/segment_march_2026-170426.xlsx",
        "source_file": "data/agent-pulls/industry-segment-history/sources/segment_march_2026-170426.xlsx",
        "source_period": "FY25",
        "fetched_at": "2026-06-10T17:08:07.151Z",
        "parsed_at": "2026-06-10T17:08:07.353Z",
        "parser_name": "ingest-gicouncil-segment-annual",
        "confidence": "high"
      }
    },
    {
      "fiscal_year": "FY25",
      "entity": "united-india",
      "carrier_group": "general",
      "insurer_name": "United India Insurance Co Ltd",
      "health_retail": 1718.77,
      "health_group": 3545.61,
      "health_govt": 1765.97,
      "overseas_medical": 3.94,
      "health_total": 7034.29,
      "basis": "as printed in the report",
      "source_basis": "prior-year comparative columns",
      "period_label": "For the period up to March 2025",
      "provenance": {
        "source_name": "GI Council Segment-wise Report (upto March 2026 (FY26, provisional & unaudited)) — prior-year comparative columns",
        "source_url": "https://www.gicouncil.in/media/4638/segment_march_2026-170426.xlsx",
        "source_file": "data/agent-pulls/industry-segment-history/sources/segment_march_2026-170426.xlsx",
        "source_period": "FY25",
        "fetched_at": "2026-06-10T17:08:07.151Z",
        "parsed_at": "2026-06-10T17:08:07.353Z",
        "parser_name": "ingest-gicouncil-segment-annual",
        "confidence": "high"
      }
    },
    {
      "fiscal_year": "FY25",
      "entity": "niva-bupa",
      "carrier_group": "sahi",
      "insurer_name": "Niva bupa health insurance company limited",
      "health_retail": 4432.5,
      "health_group": 2183.84,
      "health_govt": 0,
      "overseas_medical": 18.19,
      "health_total": 6634.53,
      "basis": "as printed in the report",
      "source_basis": "prior-year comparative columns",
      "period_label": "For the period up to March 2025",
      "provenance": {
        "source_name": "GI Council Segment-wise Report (upto March 2026 (FY26, provisional & unaudited)) — prior-year comparative columns",
        "source_url": "https://www.gicouncil.in/media/4638/segment_march_2026-170426.xlsx",
        "source_file": "data/agent-pulls/industry-segment-history/sources/segment_march_2026-170426.xlsx",
        "source_period": "FY25",
        "fetched_at": "2026-06-10T17:08:07.151Z",
        "parsed_at": "2026-06-10T17:08:07.353Z",
        "parser_name": "ingest-gicouncil-segment-annual",
        "confidence": "high"
      }
    },
    {
      "fiscal_year": "FY25",
      "entity": "aditya-birla",
      "carrier_group": "sahi",
      "insurer_name": "Aditya Birla Health Insurance Co Ltd",
      "health_retail": 1440.17,
      "health_group": 2956.87,
      "health_govt": 0,
      "overseas_medical": 49.77,
      "health_total": 4446.81,
      "basis": "as printed in the report",
      "source_basis": "prior-year comparative columns",
      "period_label": "For the period up to March 2025",
      "provenance": {
        "source_name": "GI Council Segment-wise Report (upto March 2026 (FY26, provisional & unaudited)) — prior-year comparative columns",
        "source_url": "https://www.gicouncil.in/media/4638/segment_march_2026-170426.xlsx",
        "source_file": "data/agent-pulls/industry-segment-history/sources/segment_march_2026-170426.xlsx",
        "source_period": "FY25",
        "fetched_at": "2026-06-10T17:08:07.151Z",
        "parsed_at": "2026-06-10T17:08:07.353Z",
        "parser_name": "ingest-gicouncil-segment-annual",
        "confidence": "high"
      }
    },
    {
      "fiscal_year": "FY25",
      "entity": "care-health",
      "carrier_group": "sahi",
      "insurer_name": "Care Health Insurance Ltd",
      "health_retail": 5111.36,
      "health_group": 2885.03,
      "health_govt": 0,
      "overseas_medical": 117.27,
      "health_total": 8113.66,
      "basis": "as printed in the report",
      "source_basis": "prior-year comparative columns",
      "period_label": "For the period up to March 2025",
      "provenance": {
        "source_name": "GI Council Segment-wise Report (upto March 2026 (FY26, provisional & unaudited)) — prior-year comparative columns",
        "source_url": "https://www.gicouncil.in/media/4638/segment_march_2026-170426.xlsx",
        "source_file": "data/agent-pulls/industry-segment-history/sources/segment_march_2026-170426.xlsx",
        "source_period": "FY25",
        "fetched_at": "2026-06-10T17:08:07.151Z",
        "parsed_at": "2026-06-10T17:08:07.353Z",
        "parser_name": "ingest-gicouncil-segment-annual",
        "confidence": "high"
      }
    },
    {
      "fiscal_year": "FY25",
      "entity": "galaxy-health",
      "carrier_group": "sahi",
      "insurer_name": "Galaxy Health Insurance Company Ltd",
      "health_retail": 13.99,
      "health_group": 2.09,
      "health_govt": 0,
      "overseas_medical": 0,
      "health_total": 16.08,
      "basis": "as printed in the report",
      "source_basis": "prior-year comparative columns",
      "period_label": "For the period up to March 2025",
      "provenance": {
        "source_name": "GI Council Segment-wise Report (upto March 2026 (FY26, provisional & unaudited)) — prior-year comparative columns",
        "source_url": "https://www.gicouncil.in/media/4638/segment_march_2026-170426.xlsx",
        "source_file": "data/agent-pulls/industry-segment-history/sources/segment_march_2026-170426.xlsx",
        "source_period": "FY25",
        "fetched_at": "2026-06-10T17:08:07.151Z",
        "parsed_at": "2026-06-10T17:08:07.353Z",
        "parser_name": "ingest-gicouncil-segment-annual",
        "confidence": "high"
      }
    },
    {
      "fiscal_year": "FY25",
      "entity": "manipalcigna",
      "carrier_group": "sahi",
      "insurer_name": "ManipalCigna Health Insurance Co Ltd",
      "health_retail": 841.12,
      "health_group": 923.59,
      "health_govt": 0,
      "overseas_medical": 2.83,
      "health_total": 1767.54,
      "basis": "as printed in the report",
      "source_basis": "prior-year comparative columns",
      "period_label": "For the period up to March 2025",
      "provenance": {
        "source_name": "GI Council Segment-wise Report (upto March 2026 (FY26, provisional & unaudited)) — prior-year comparative columns",
        "source_url": "https://www.gicouncil.in/media/4638/segment_march_2026-170426.xlsx",
        "source_file": "data/agent-pulls/industry-segment-history/sources/segment_march_2026-170426.xlsx",
        "source_period": "FY25",
        "fetched_at": "2026-06-10T17:08:07.151Z",
        "parsed_at": "2026-06-10T17:08:07.353Z",
        "parser_name": "ingest-gicouncil-segment-annual",
        "confidence": "high"
      }
    },
    {
      "fiscal_year": "FY25",
      "entity": "narayana-health",
      "carrier_group": "sahi",
      "insurer_name": "Narayana Health Insurance Ltd",
      "health_retail": 0,
      "health_group": 0,
      "health_govt": 0,
      "overseas_medical": 0,
      "health_total": 0,
      "basis": "as printed in the report",
      "source_basis": "prior-year comparative columns",
      "period_label": "For the period up to March 2025",
      "provenance": {
        "source_name": "GI Council Segment-wise Report (upto March 2026 (FY26, provisional & unaudited)) — prior-year comparative columns",
        "source_url": "https://www.gicouncil.in/media/4638/segment_march_2026-170426.xlsx",
        "source_file": "data/agent-pulls/industry-segment-history/sources/segment_march_2026-170426.xlsx",
        "source_period": "FY25",
        "fetched_at": "2026-06-10T17:08:07.151Z",
        "parsed_at": "2026-06-10T17:08:07.353Z",
        "parser_name": "ingest-gicouncil-segment-annual",
        "confidence": "high"
      }
    },
    {
      "fiscal_year": "FY25",
      "entity": "star-health",
      "carrier_group": "sahi",
      "insurer_name": "Star Health & Allied Insurance Co Ltd",
      "health_retail": 15413,
      "health_group": 1103.77,
      "health_govt": 0,
      "overseas_medical": 9.48,
      "health_total": 16526.25,
      "basis": "as printed in the report",
      "source_basis": "prior-year comparative columns",
      "period_label": "For the period up to March 2025",
      "provenance": {
        "source_name": "GI Council Segment-wise Report (upto March 2026 (FY26, provisional & unaudited)) — prior-year comparative columns",
        "source_url": "https://www.gicouncil.in/media/4638/segment_march_2026-170426.xlsx",
        "source_file": "data/agent-pulls/industry-segment-history/sources/segment_march_2026-170426.xlsx",
        "source_period": "FY25",
        "fetched_at": "2026-06-10T17:08:07.151Z",
        "parsed_at": "2026-06-10T17:08:07.353Z",
        "parser_name": "ingest-gicouncil-segment-annual",
        "confidence": "high"
      }
    },
    {
      "fiscal_year": "FY25",
      "entity": "GENERAL",
      "carrier_group": "aggregate",
      "insurer_name": "General Insurers Sub Total (as printed)",
      "health_retail": 20036.14,
      "health_group": 50753.76,
      "health_govt": 9417.15,
      "overseas_medical": 1145.71,
      "health_total": 81352.76,
      "basis": "as printed in the report",
      "source_basis": "prior-year comparative columns",
      "period_label": "For the period up to March 2025",
      "provenance": {
        "source_name": "GI Council Segment-wise Report (upto March 2026 (FY26, provisional & unaudited)) — prior-year comparative columns",
        "source_url": "https://www.gicouncil.in/media/4638/segment_march_2026-170426.xlsx",
        "source_file": "data/agent-pulls/industry-segment-history/sources/segment_march_2026-170426.xlsx",
        "source_period": "FY25",
        "fetched_at": "2026-06-10T17:08:07.151Z",
        "parsed_at": "2026-06-10T17:08:07.353Z",
        "parser_name": "ingest-gicouncil-segment-annual",
        "confidence": "high"
      }
    },
    {
      "fiscal_year": "FY25",
      "entity": "SAHI",
      "carrier_group": "aggregate",
      "insurer_name": "Stand-alone Health sub Total (as printed)",
      "health_retail": 27252.14,
      "health_group": 10055.19,
      "health_govt": 0,
      "overseas_medical": 197.54,
      "health_total": 37504.87,
      "basis": "as printed in the report",
      "source_basis": "prior-year comparative columns",
      "period_label": "For the period up to March 2025",
      "provenance": {
        "source_name": "GI Council Segment-wise Report (upto March 2026 (FY26, provisional & unaudited)) — prior-year comparative columns",
        "source_url": "https://www.gicouncil.in/media/4638/segment_march_2026-170426.xlsx",
        "source_file": "data/agent-pulls/industry-segment-history/sources/segment_march_2026-170426.xlsx",
        "source_period": "FY25",
        "fetched_at": "2026-06-10T17:08:07.151Z",
        "parsed_at": "2026-06-10T17:08:07.353Z",
        "parser_name": "ingest-gicouncil-segment-annual",
        "confidence": "high"
      }
    },
    {
      "fiscal_year": "FY25",
      "entity": "INDUSTRY",
      "carrier_group": "aggregate",
      "insurer_name": "Industry Total (as printed)",
      "health_retail": 47288.28,
      "health_group": 60808.95,
      "health_govt": 9417.15,
      "overseas_medical": 1343.25,
      "health_total": 118857.63,
      "basis": "as printed in the report",
      "source_basis": "prior-year comparative columns",
      "period_label": "For the period up to March 2025",
      "provenance": {
        "source_name": "GI Council Segment-wise Report (upto March 2026 (FY26, provisional & unaudited)) — prior-year comparative columns",
        "source_url": "https://www.gicouncil.in/media/4638/segment_march_2026-170426.xlsx",
        "source_file": "data/agent-pulls/industry-segment-history/sources/segment_march_2026-170426.xlsx",
        "source_period": "FY25",
        "fetched_at": "2026-06-10T17:08:07.151Z",
        "parsed_at": "2026-06-10T17:08:07.353Z",
        "parser_name": "ingest-gicouncil-segment-annual",
        "confidence": "high"
      }
    },
    {
      "fiscal_year": "FY25",
      "entity": "PSUs",
      "carrier_group": "aggregate",
      "insurer_name": "Public-sector general insurers",
      "health_retail": 9444.1,
      "health_group": 27135.64,
      "health_govt": 5841.04,
      "overseas_medical": 18.59,
      "health_total": 42439.37,
      "basis": "derived: sum of the printed National + New India + Oriental + United India rows",
      "source_basis": "prior-year comparative columns",
      "period_label": "For the period up to March 2025",
      "provenance": {
        "source_name": "GI Council Segment-wise Report (upto March 2026 (FY26, provisional & unaudited)) — prior-year comparative columns",
        "source_url": "https://www.gicouncil.in/media/4638/segment_march_2026-170426.xlsx",
        "source_file": "data/agent-pulls/industry-segment-history/sources/segment_march_2026-170426.xlsx",
        "source_period": "FY25",
        "fetched_at": "2026-06-10T17:08:07.151Z",
        "parsed_at": "2026-06-10T17:08:07.353Z",
        "parser_name": "ingest-gicouncil-segment-annual",
        "confidence": "high"
      }
    },
    {
      "fiscal_year": "FY25",
      "entity": "Private",
      "carrier_group": "aggregate",
      "insurer_name": "Private general insurers",
      "health_retail": 10592.04,
      "health_group": 23618.12,
      "health_govt": 3576.11,
      "overseas_medical": 1127.12,
      "health_total": 38913.39,
      "basis": "derived: printed General Insurers Sub Total − the 4 public-sector insurers",
      "source_basis": "prior-year comparative columns",
      "period_label": "For the period up to March 2025",
      "provenance": {
        "source_name": "GI Council Segment-wise Report (upto March 2026 (FY26, provisional & unaudited)) — prior-year comparative columns",
        "source_url": "https://www.gicouncil.in/media/4638/segment_march_2026-170426.xlsx",
        "source_file": "data/agent-pulls/industry-segment-history/sources/segment_march_2026-170426.xlsx",
        "source_period": "FY25",
        "fetched_at": "2026-06-10T17:08:07.151Z",
        "parsed_at": "2026-06-10T17:08:07.353Z",
        "parser_name": "ingest-gicouncil-segment-annual",
        "confidence": "high"
      }
    },
    {
      "fiscal_year": "FY25",
      "entity": "Others",
      "carrier_group": "aggregate",
      "insurer_name": "All other insurers (retail health)",
      "health_retail": 4837.1,
      "health_group": null,
      "health_govt": null,
      "overseas_medical": null,
      "health_total": null,
      "basis": "derived: printed Industry Total retail − the 11 named insurer rows",
      "source_basis": "prior-year comparative columns",
      "period_label": "For the period up to March 2025",
      "provenance": {
        "source_name": "GI Council Segment-wise Report (upto March 2026 (FY26, provisional & unaudited)) — prior-year comparative columns",
        "source_url": "https://www.gicouncil.in/media/4638/segment_march_2026-170426.xlsx",
        "source_file": "data/agent-pulls/industry-segment-history/sources/segment_march_2026-170426.xlsx",
        "source_period": "FY25",
        "fetched_at": "2026-06-10T17:08:07.151Z",
        "parsed_at": "2026-06-10T17:08:07.353Z",
        "parser_name": "ingest-gicouncil-segment-annual",
        "confidence": "high"
      }
    },
    {
      "fiscal_year": "FY26",
      "entity": "hdfc-ergo",
      "carrier_group": "general",
      "insurer_name": "HDFC Ergo General Insurance Co Ltd",
      "health_retail": 5155.8,
      "health_group": 1460.26,
      "health_govt": 0,
      "overseas_medical": 56.67,
      "health_total": 6672.73,
      "basis": "as printed in the report",
      "source_basis": "current-year columns",
      "period_label": "For the period up to March 2026",
      "provenance": {
        "source_name": "GI Council Segment-wise Report (upto March 2026 (FY26, provisional & unaudited)) — current-year columns",
        "source_url": "https://www.gicouncil.in/media/4638/segment_march_2026-170426.xlsx",
        "source_file": "data/agent-pulls/industry-segment-history/sources/segment_march_2026-170426.xlsx",
        "source_period": "FY26",
        "fetched_at": "2026-06-10T17:07:57.519Z",
        "parsed_at": "2026-06-10T17:07:57.709Z",
        "parser_name": "ingest-gicouncil-segment-annual",
        "confidence": "high"
      }
    },
    {
      "fiscal_year": "FY26",
      "entity": "icici-lombard",
      "carrier_group": "general",
      "insurer_name": "ICICI Lombard General Insurance Co Ltd",
      "health_retail": 2351.2,
      "health_group": 5989.49,
      "health_govt": 0,
      "overseas_medical": 276.59,
      "health_total": 8617.28,
      "basis": "as printed in the report",
      "source_basis": "current-year columns",
      "period_label": "For the period up to March 2026",
      "provenance": {
        "source_name": "GI Council Segment-wise Report (upto March 2026 (FY26, provisional & unaudited)) — current-year columns",
        "source_url": "https://www.gicouncil.in/media/4638/segment_march_2026-170426.xlsx",
        "source_file": "data/agent-pulls/industry-segment-history/sources/segment_march_2026-170426.xlsx",
        "source_period": "FY26",
        "fetched_at": "2026-06-10T17:07:57.519Z",
        "parsed_at": "2026-06-10T17:07:57.709Z",
        "parser_name": "ingest-gicouncil-segment-annual",
        "confidence": "high"
      }
    },
    {
      "fiscal_year": "FY26",
      "entity": "national-insurance",
      "carrier_group": "general",
      "insurer_name": "National Insurance Co Ltd",
      "health_retail": 2619.65,
      "health_group": 4919.77,
      "health_govt": 735.74,
      "overseas_medical": 3.62,
      "health_total": 8278.78,
      "basis": "as printed in the report",
      "source_basis": "current-year columns",
      "period_label": "For the period up to March 2026",
      "provenance": {
        "source_name": "GI Council Segment-wise Report (upto March 2026 (FY26, provisional & unaudited)) — current-year columns",
        "source_url": "https://www.gicouncil.in/media/4638/segment_march_2026-170426.xlsx",
        "source_file": "data/agent-pulls/industry-segment-history/sources/segment_march_2026-170426.xlsx",
        "source_period": "FY26",
        "fetched_at": "2026-06-10T17:04:18.008Z",
        "parsed_at": "2026-06-10T17:04:18.201Z",
        "parser_name": "ingest-gicouncil-segment-annual",
        "confidence": "high"
      }
    },
    {
      "fiscal_year": "FY26",
      "entity": "new-india",
      "carrier_group": "general",
      "insurer_name": "The New India Assurance Co Ltd",
      "health_retail": 3672.81,
      "health_group": 14615.1,
      "health_govt": 3237.58,
      "overseas_medical": 6.03,
      "health_total": 21531.52,
      "basis": "as printed in the report",
      "source_basis": "current-year columns",
      "period_label": "For the period up to March 2026",
      "provenance": {
        "source_name": "GI Council Segment-wise Report (upto March 2026 (FY26, provisional & unaudited)) — current-year columns",
        "source_url": "https://www.gicouncil.in/media/4638/segment_march_2026-170426.xlsx",
        "source_file": "data/agent-pulls/industry-segment-history/sources/segment_march_2026-170426.xlsx",
        "source_period": "FY26",
        "fetched_at": "2026-06-10T17:07:57.519Z",
        "parsed_at": "2026-06-10T17:07:57.709Z",
        "parser_name": "ingest-gicouncil-segment-annual",
        "confidence": "high"
      }
    },
    {
      "fiscal_year": "FY26",
      "entity": "oriental-insurance",
      "carrier_group": "general",
      "insurer_name": "The Oriental Insurance Co Ltd",
      "health_retail": 2005.74,
      "health_group": 6191.93,
      "health_govt": 593.22,
      "overseas_medical": 3.01,
      "health_total": 8793.9,
      "basis": "as printed in the report",
      "source_basis": "current-year columns",
      "period_label": "For the period up to March 2026",
      "provenance": {
        "source_name": "GI Council Segment-wise Report (upto March 2026 (FY26, provisional & unaudited)) — current-year columns",
        "source_url": "https://www.gicouncil.in/media/4638/segment_march_2026-170426.xlsx",
        "source_file": "data/agent-pulls/industry-segment-history/sources/segment_march_2026-170426.xlsx",
        "source_period": "FY26",
        "fetched_at": "2026-06-10T17:04:18.008Z",
        "parsed_at": "2026-06-10T17:04:18.201Z",
        "parser_name": "ingest-gicouncil-segment-annual",
        "confidence": "high"
      }
    },
    {
      "fiscal_year": "FY26",
      "entity": "united-india",
      "carrier_group": "general",
      "insurer_name": "United India Insurance Co Ltd",
      "health_retail": 1796.32,
      "health_group": 4258.52,
      "health_govt": 1778.07,
      "overseas_medical": 3.4,
      "health_total": 7836.31,
      "basis": "as printed in the report",
      "source_basis": "current-year columns",
      "period_label": "For the period up to March 2026",
      "provenance": {
        "source_name": "GI Council Segment-wise Report (upto March 2026 (FY26, provisional & unaudited)) — current-year columns",
        "source_url": "https://www.gicouncil.in/media/4638/segment_march_2026-170426.xlsx",
        "source_file": "data/agent-pulls/industry-segment-history/sources/segment_march_2026-170426.xlsx",
        "source_period": "FY26",
        "fetched_at": "2026-06-10T17:07:57.519Z",
        "parsed_at": "2026-06-10T17:07:57.709Z",
        "parser_name": "ingest-gicouncil-segment-annual",
        "confidence": "high"
      }
    },
    {
      "fiscal_year": "FY26",
      "entity": "niva-bupa",
      "carrier_group": "sahi",
      "insurer_name": "Niva bupa health insurance company limited",
      "health_retail": 5747.59,
      "health_group": 2717.31,
      "health_govt": 0,
      "overseas_medical": 14.76,
      "health_total": 8479.66,
      "basis": "as printed in the report",
      "source_basis": "current-year columns",
      "period_label": "For the period up to March 2026",
      "provenance": {
        "source_name": "GI Council Segment-wise Report (upto March 2026 (FY26, provisional & unaudited)) — current-year columns",
        "source_url": "https://www.gicouncil.in/media/4638/segment_march_2026-170426.xlsx",
        "source_file": "data/agent-pulls/industry-segment-history/sources/segment_march_2026-170426.xlsx",
        "source_period": "FY26",
        "fetched_at": "2026-06-10T17:04:18.008Z",
        "parsed_at": "2026-06-10T17:04:18.201Z",
        "parser_name": "ingest-gicouncil-segment-annual",
        "confidence": "high"
      }
    },
    {
      "fiscal_year": "FY26",
      "entity": "aditya-birla",
      "carrier_group": "sahi",
      "insurer_name": "Aditya Birla Health Insurance Co Ltd",
      "health_retail": 2163.86,
      "health_group": 3633.08,
      "health_govt": 0,
      "overseas_medical": 28.53,
      "health_total": 5825.47,
      "basis": "as printed in the report",
      "source_basis": "current-year columns",
      "period_label": "For the period up to March 2026",
      "provenance": {
        "source_name": "GI Council Segment-wise Report (upto March 2026 (FY26, provisional & unaudited)) — current-year columns",
        "source_url": "https://www.gicouncil.in/media/4638/segment_march_2026-170426.xlsx",
        "source_file": "data/agent-pulls/industry-segment-history/sources/segment_march_2026-170426.xlsx",
        "source_period": "FY26",
        "fetched_at": "2026-06-10T17:04:18.008Z",
        "parsed_at": "2026-06-10T17:04:18.201Z",
        "parser_name": "ingest-gicouncil-segment-annual",
        "confidence": "high"
      }
    },
    {
      "fiscal_year": "FY26",
      "entity": "care-health",
      "carrier_group": "sahi",
      "insurer_name": "Care Health Insurance Ltd",
      "health_retail": 6597.6,
      "health_group": 3060.47,
      "health_govt": 0,
      "overseas_medical": 110.33,
      "health_total": 9768.4,
      "basis": "as printed in the report",
      "source_basis": "current-year columns",
      "period_label": "For the period up to March 2026",
      "provenance": {
        "source_name": "GI Council Segment-wise Report (upto March 2026 (FY26, provisional & unaudited)) — current-year columns",
        "source_url": "https://www.gicouncil.in/media/4638/segment_march_2026-170426.xlsx",
        "source_file": "data/agent-pulls/industry-segment-history/sources/segment_march_2026-170426.xlsx",
        "source_period": "FY26",
        "fetched_at": "2026-06-10T17:04:18.008Z",
        "parsed_at": "2026-06-10T17:04:18.201Z",
        "parser_name": "ingest-gicouncil-segment-annual",
        "confidence": "high"
      }
    },
    {
      "fiscal_year": "FY26",
      "entity": "galaxy-health",
      "carrier_group": "sahi",
      "insurer_name": "Galaxy Health Insurance Company Ltd",
      "health_retail": 97.46,
      "health_group": 43.54,
      "health_govt": 0,
      "overseas_medical": 0,
      "health_total": 141,
      "basis": "as printed in the report",
      "source_basis": "current-year columns",
      "period_label": "For the period up to March 2026",
      "provenance": {
        "source_name": "GI Council Segment-wise Report (upto March 2026 (FY26, provisional & unaudited)) — current-year columns",
        "source_url": "https://www.gicouncil.in/media/4638/segment_march_2026-170426.xlsx",
        "source_file": "data/agent-pulls/industry-segment-history/sources/segment_march_2026-170426.xlsx",
        "source_period": "FY26",
        "fetched_at": "2026-06-10T17:04:18.008Z",
        "parsed_at": "2026-06-10T17:04:18.201Z",
        "parser_name": "ingest-gicouncil-segment-annual",
        "confidence": "high"
      }
    },
    {
      "fiscal_year": "FY26",
      "entity": "manipalcigna",
      "carrier_group": "sahi",
      "insurer_name": "ManipalCigna Health Insurance Co Ltd",
      "health_retail": 1119.03,
      "health_group": 1049.21,
      "health_govt": 0,
      "overseas_medical": 2.07,
      "health_total": 2170.31,
      "basis": "as printed in the report",
      "source_basis": "current-year columns",
      "period_label": "For the period up to March 2026",
      "provenance": {
        "source_name": "GI Council Segment-wise Report (upto March 2026 (FY26, provisional & unaudited)) — current-year columns",
        "source_url": "https://www.gicouncil.in/media/4638/segment_march_2026-170426.xlsx",
        "source_file": "data/agent-pulls/industry-segment-history/sources/segment_march_2026-170426.xlsx",
        "source_period": "FY26",
        "fetched_at": "2026-06-10T17:04:18.008Z",
        "parsed_at": "2026-06-10T17:04:18.201Z",
        "parser_name": "ingest-gicouncil-segment-annual",
        "confidence": "high"
      }
    },
    {
      "fiscal_year": "FY26",
      "entity": "narayana-health",
      "carrier_group": "sahi",
      "insurer_name": "Narayana Health Insurance Ltd",
      "health_retail": 9.05,
      "health_group": 34.8,
      "health_govt": 0,
      "overseas_medical": 0,
      "health_total": 43.85,
      "basis": "as printed in the report",
      "source_basis": "current-year columns",
      "period_label": "For the period up to March 2026",
      "provenance": {
        "source_name": "GI Council Segment-wise Report (upto March 2026 (FY26, provisional & unaudited)) — current-year columns",
        "source_url": "https://www.gicouncil.in/media/4638/segment_march_2026-170426.xlsx",
        "source_file": "data/agent-pulls/industry-segment-history/sources/segment_march_2026-170426.xlsx",
        "source_period": "FY26",
        "fetched_at": "2026-06-10T17:07:57.519Z",
        "parsed_at": "2026-06-10T17:07:57.709Z",
        "parser_name": "ingest-gicouncil-segment-annual",
        "confidence": "high"
      }
    },
    {
      "fiscal_year": "FY26",
      "entity": "star-health",
      "carrier_group": "sahi",
      "insurer_name": "Star Health & Allied Insurance Co Ltd",
      "health_retail": 17743,
      "health_group": 683.87,
      "health_govt": 0,
      "overseas_medical": 8.17,
      "health_total": 18435.04,
      "basis": "as printed in the report",
      "source_basis": "current-year columns",
      "period_label": "For the period up to March 2026",
      "provenance": {
        "source_name": "GI Council Segment-wise Report (upto March 2026 (FY26, provisional & unaudited)) — current-year columns",
        "source_url": "https://www.gicouncil.in/media/4638/segment_march_2026-170426.xlsx",
        "source_file": "data/agent-pulls/industry-segment-history/sources/segment_march_2026-170426.xlsx",
        "source_period": "FY26",
        "fetched_at": "2026-06-10T17:07:57.519Z",
        "parsed_at": "2026-06-10T17:07:57.709Z",
        "parser_name": "ingest-gicouncil-segment-annual",
        "confidence": "high"
      }
    },
    {
      "fiscal_year": "FY26",
      "entity": "GENERAL",
      "carrier_group": "aggregate",
      "insurer_name": "General Insurers Sub Total (as printed)",
      "health_retail": 23218.2,
      "health_group": 57419.2,
      "health_govt": 10318.33,
      "overseas_medical": 1325,
      "health_total": 92280.73,
      "basis": "as printed in the report",
      "source_basis": "current-year columns",
      "period_label": "For the period up to March 2026",
      "provenance": {
        "source_name": "GI Council Segment-wise Report (upto March 2026 (FY26, provisional & unaudited)) — current-year columns",
        "source_url": "https://www.gicouncil.in/media/4638/segment_march_2026-170426.xlsx",
        "source_file": "data/agent-pulls/industry-segment-history/sources/segment_march_2026-170426.xlsx",
        "source_period": "FY26",
        "fetched_at": "2026-06-10T17:07:57.519Z",
        "parsed_at": "2026-06-10T17:07:57.709Z",
        "parser_name": "ingest-gicouncil-segment-annual",
        "confidence": "high"
      }
    },
    {
      "fiscal_year": "FY26",
      "entity": "SAHI",
      "carrier_group": "aggregate",
      "insurer_name": "Stand-alone Health sub Total (as printed)",
      "health_retail": 33477.59,
      "health_group": 11222.28,
      "health_govt": 0,
      "overseas_medical": 163.86,
      "health_total": 44863.73,
      "basis": "as printed in the report",
      "source_basis": "current-year columns",
      "period_label": "For the period up to March 2026",
      "provenance": {
        "source_name": "GI Council Segment-wise Report (upto March 2026 (FY26, provisional & unaudited)) — current-year columns",
        "source_url": "https://www.gicouncil.in/media/4638/segment_march_2026-170426.xlsx",
        "source_file": "data/agent-pulls/industry-segment-history/sources/segment_march_2026-170426.xlsx",
        "source_period": "FY26",
        "fetched_at": "2026-06-10T17:07:57.519Z",
        "parsed_at": "2026-06-10T17:07:57.709Z",
        "parser_name": "ingest-gicouncil-segment-annual",
        "confidence": "high"
      }
    },
    {
      "fiscal_year": "FY26",
      "entity": "INDUSTRY",
      "carrier_group": "aggregate",
      "insurer_name": "Industry Total (as printed)",
      "health_retail": 56695.79,
      "health_group": 68641.48,
      "health_govt": 10318.33,
      "overseas_medical": 1488.86,
      "health_total": 137144.46,
      "basis": "as printed in the report",
      "source_basis": "current-year columns",
      "period_label": "For the period up to March 2026",
      "provenance": {
        "source_name": "GI Council Segment-wise Report (upto March 2026 (FY26, provisional & unaudited)) — current-year columns",
        "source_url": "https://www.gicouncil.in/media/4638/segment_march_2026-170426.xlsx",
        "source_file": "data/agent-pulls/industry-segment-history/sources/segment_march_2026-170426.xlsx",
        "source_period": "FY26",
        "fetched_at": "2026-06-10T17:07:57.519Z",
        "parsed_at": "2026-06-10T17:07:57.709Z",
        "parser_name": "ingest-gicouncil-segment-annual",
        "confidence": "high"
      }
    },
    {
      "fiscal_year": "FY26",
      "entity": "PSUs",
      "carrier_group": "aggregate",
      "insurer_name": "Public-sector general insurers",
      "health_retail": 10094.52,
      "health_group": 29985.32,
      "health_govt": 6344.61,
      "overseas_medical": 16.06,
      "health_total": 46440.51,
      "basis": "derived: sum of the printed National + New India + Oriental + United India rows",
      "source_basis": "current-year columns",
      "period_label": "For the period up to March 2026",
      "provenance": {
        "source_name": "GI Council Segment-wise Report (upto March 2026 (FY26, provisional & unaudited)) — current-year columns",
        "source_url": "https://www.gicouncil.in/media/4638/segment_march_2026-170426.xlsx",
        "source_file": "data/agent-pulls/industry-segment-history/sources/segment_march_2026-170426.xlsx",
        "source_period": "FY26",
        "fetched_at": "2026-06-10T17:04:18.008Z",
        "parsed_at": "2026-06-10T17:04:18.201Z",
        "parser_name": "ingest-gicouncil-segment-annual",
        "confidence": "high"
      }
    },
    {
      "fiscal_year": "FY26",
      "entity": "Private",
      "carrier_group": "aggregate",
      "insurer_name": "Private general insurers",
      "health_retail": 13123.68,
      "health_group": 27433.88,
      "health_govt": 3973.72,
      "overseas_medical": 1308.94,
      "health_total": 45840.22,
      "basis": "derived: printed General Insurers Sub Total − the 4 public-sector insurers",
      "source_basis": "current-year columns",
      "period_label": "For the period up to March 2026",
      "provenance": {
        "source_name": "GI Council Segment-wise Report (upto March 2026 (FY26, provisional & unaudited)) — current-year columns",
        "source_url": "https://www.gicouncil.in/media/4638/segment_march_2026-170426.xlsx",
        "source_file": "data/agent-pulls/industry-segment-history/sources/segment_march_2026-170426.xlsx",
        "source_period": "FY26",
        "fetched_at": "2026-06-10T17:04:18.008Z",
        "parsed_at": "2026-06-10T17:04:18.201Z",
        "parser_name": "ingest-gicouncil-segment-annual",
        "confidence": "high"
      }
    },
    {
      "fiscal_year": "FY26",
      "entity": "Others",
      "carrier_group": "aggregate",
      "insurer_name": "All other insurers (retail health)",
      "health_retail": 5723.19,
      "health_group": null,
      "health_govt": null,
      "overseas_medical": null,
      "health_total": null,
      "basis": "derived: printed Industry Total retail − the 11 named insurer rows",
      "source_basis": "current-year columns",
      "period_label": "For the period up to March 2026",
      "provenance": {
        "source_name": "GI Council Segment-wise Report (upto March 2026 (FY26, provisional & unaudited)) — current-year columns",
        "source_url": "https://www.gicouncil.in/media/4638/segment_march_2026-170426.xlsx",
        "source_file": "data/agent-pulls/industry-segment-history/sources/segment_march_2026-170426.xlsx",
        "source_period": "FY26",
        "fetched_at": "2026-06-10T17:04:18.008Z",
        "parsed_at": "2026-06-10T17:04:18.201Z",
        "parser_name": "ingest-gicouncil-segment-annual",
        "confidence": "high"
      }
    }
  ]
}
